cleangram/__init__.py
cleangram-0.0.0.dev3.dist-info/WHEEL
cleangram-0.0.0.dev3.dist-info/METADATA
cleangram-0.0.0.dev3.dist-info/RECORD
