Metadata-Version: 2.1
Name: cleangram
Version: 0.0.0.dev3
Summary: Simple framework for develop telegram bots
Author: Arwichok
Author-email: me@arwi.dev
Requires-Python: >=3.8,<4.0
Classifier: Programming Language :: Python :: 3
Classifier: Programming Language :: Python :: 3.10
Classifier: Programming Language :: Python :: 3.8
Classifier: Programming Language :: Python :: 3.9
